bridge_service/__init__.py
bridge_service/service.py
bridge_service-0.1.2.dist-info/METADATA
bridge_service-0.1.2.dist-info/WHEEL
bridge_service-0.1.2.dist-info/top_level.txt
bridge_service-0.1.2.dist-info/RECORD
