Metadata-Version: 2.4
Name: bridge-service
Version: 0.1.2
Summary: This package contains the core logic for conversational flows for an Amigo phone agent
Author-email: Ezeugo <ezeugo@amigo.ai>
Requires-Python: >=3.13
